{
    "last_updated": "2026-05-04 05:26:45",
    "districts": {
        "LCPS": {
            "forecasts": [
                {
                    "date": "2026-05-04",
                    "label": "Monday, May 04",
                    "primary_prediction": "Open",
                    "probabilities": {
                        "open": 91.2,
                        "delay": 4.6,
                        "early_release": 1.1,
                        "closure": 3.1
                    }
                },
                {
                    "date": "2026-05-05",
                    "label": "Tuesday, May 05",
                    "primary_prediction": "Open",
                    "probabilities": {
                        "open": 80.3,
                        "delay": 9.0,
                        "early_release": 1.9,
                        "closure": 8.8
                    }
                },
                {
                    "date": "2026-05-06",
                    "label": "Wednesday, May 06",
                    "primary_prediction": "Open",
                    "probabilities": {
                        "open": 56.2,
                        "delay": 29.0,
                        "early_release": 2.6,
                        "closure": 12.2
                    }
                }
            ]
        },
        "FCPS": {
            "forecasts": [
                {
                    "date": "2026-05-04",
                    "label": "Monday, May 04",
                    "primary_prediction": "Open",
                    "probabilities": {
                        "open": 84.2,
                        "delay": 10.6,
                        "early_release": 1.8,
                        "closure": 3.4
                    }
                },
                {
                    "date": "2026-05-05",
                    "label": "Tuesday, May 05",
                    "primary_prediction": "Open",
                    "probabilities": {
                        "open": 72.8,
                        "delay": 20.4,
                        "early_release": 2.4,
                        "closure": 4.4
                    }
                },
                {
                    "date": "2026-05-06",
                    "label": "Wednesday, May 06",
                    "primary_prediction": "Open",
                    "probabilities": {
                        "open": 61.0,
                        "delay": 31.9,
                        "early_release": 2.9,
                        "closure": 4.2
                    }
                }
            ]
        },
        "PWCS": {
            "forecasts": [
                {
                    "date": "2026-05-04",
                    "label": "Monday, May 04",
                    "primary_prediction": "Open",
                    "probabilities": {
                        "open": 93.9,
                        "delay": 3.5,
                        "early_release": 1.0,
                        "closure": 1.6
                    }
                },
                {
                    "date": "2026-05-05",
                    "label": "Tuesday, May 05",
                    "primary_prediction": "Open",
                    "probabilities": {
                        "open": 87.4,
                        "delay": 7.2,
                        "early_release": 2.0,
                        "closure": 3.4
                    }
                },
                {
                    "date": "2026-05-06",
                    "label": "Wednesday, May 06",
                    "primary_prediction": "Open",
                    "probabilities": {
                        "open": 81.0,
                        "delay": 9.7,
                        "early_release": 2.6,
                        "closure": 6.7
                    }
                }
            ]
        }
    },
    "forecasts": [
        {
            "date": "2026-05-04",
            "label": "Monday, May 04",
            "primary_prediction": "Open",
            "probabilities": {
                "open": 91.2,
                "delay": 4.6,
                "early_release": 1.1,
                "closure": 3.1
            }
        },
        {
            "date": "2026-05-05",
            "label": "Tuesday, May 05",
            "primary_prediction": "Open",
            "probabilities": {
                "open": 80.3,
                "delay": 9.0,
                "early_release": 1.9,
                "closure": 8.8
            }
        },
        {
            "date": "2026-05-06",
            "label": "Wednesday, May 06",
            "primary_prediction": "Open",
            "probabilities": {
                "open": 56.2,
                "delay": 29.0,
                "early_release": 2.6,
                "closure": 12.2
            }
        }
    ]
}