{
    "last_updated": "2026-07-15 18:55:08",
    "districts": {
        "LCPS": {
            "forecasts": [
                {
                    "date": "2026-07-15",
                    "label": "Wednesday, Jul 15",
                    "primary_prediction": "Open",
                    "probabilities": {
                        "open": 91.4,
                        "delay": 5.2,
                        "early_release": 1.7,
                        "closure": 1.7
                    }
                },
                {
                    "date": "2026-07-16",
                    "label": "Thursday, Jul 16",
                    "primary_prediction": "Open",
                    "probabilities": {
                        "open": 92.7,
                        "delay": 3.4,
                        "early_release": 1.1,
                        "closure": 2.8
                    }
                },
                {
                    "date": "2026-07-17",
                    "label": "Friday, Jul 17",
                    "primary_prediction": "Open",
                    "probabilities": {
                        "open": 55.8,
                        "delay": 25.7,
                        "early_release": 2.8,
                        "closure": 15.7
                    }
                }
            ]
        },
        "FCPS": {
            "forecasts": [
                {
                    "date": "2026-07-15",
                    "label": "Wednesday, Jul 15",
                    "primary_prediction": "Open",
                    "probabilities": {
                        "open": 89.8,
                        "delay": 7.0,
                        "early_release": 2.1,
                        "closure": 1.1
                    }
                },
                {
                    "date": "2026-07-16",
                    "label": "Thursday, Jul 16",
                    "primary_prediction": "Open",
                    "probabilities": {
                        "open": 90.3,
                        "delay": 6.8,
                        "early_release": 1.6,
                        "closure": 1.2
                    }
                },
                {
                    "date": "2026-07-17",
                    "label": "Friday, Jul 17",
                    "primary_prediction": "Open",
                    "probabilities": {
                        "open": 53.6,
                        "delay": 41.6,
                        "early_release": 2.9,
                        "closure": 1.9
                    }
                }
            ]
        },
        "PWCS": {
            "forecasts": [
                {
                    "date": "2026-07-15",
                    "label": "Wednesday, Jul 15",
                    "primary_prediction": "Open",
                    "probabilities": {
                        "open": 89.0,
                        "delay": 7.6,
                        "early_release": 2.3,
                        "closure": 1.1
                    }
                },
                {
                    "date": "2026-07-16",
                    "label": "Thursday, Jul 16",
                    "primary_prediction": "Open",
                    "probabilities": {
                        "open": 89.5,
                        "delay": 7.3,
                        "early_release": 1.8,
                        "closure": 1.4
                    }
                },
                {
                    "date": "2026-07-17",
                    "label": "Friday, Jul 17",
                    "primary_prediction": "Open",
                    "probabilities": {
                        "open": 70.8,
                        "delay": 18.7,
                        "early_release": 4.6,
                        "closure": 5.9
                    }
                }
            ]
        }
    },
    "forecasts": [
        {
            "date": "2026-07-15",
            "label": "Wednesday, Jul 15",
            "primary_prediction": "Open",
            "probabilities": {
                "open": 91.4,
                "delay": 5.2,
                "early_release": 1.7,
                "closure": 1.7
            }
        },
        {
            "date": "2026-07-16",
            "label": "Thursday, Jul 16",
            "primary_prediction": "Open",
            "probabilities": {
                "open": 92.7,
                "delay": 3.4,
                "early_release": 1.1,
                "closure": 2.8
            }
        },
        {
            "date": "2026-07-17",
            "label": "Friday, Jul 17",
            "primary_prediction": "Open",
            "probabilities": {
                "open": 55.8,
                "delay": 25.7,
                "early_release": 2.8,
                "closure": 15.7
            }
        }
    ]
}